{
  "project_info": {
    "project_number": "766736349135",
    "project_id": "bharat-online-7e535",
    "storage_bucket": "bharat-online-7e535.appspot.com"
  },
  "client": [
    {
      "client_info": {
        "mobilesdk_app_id": "1:766736349135:android:a5f430568d440852b944ba",
        "android_client_info": {
          "package_name": "com.bharatonline.customer.app"
        }
      },
      "oauth_client": [
        {
          "client_id": "766736349135-i08p1gj8sj99vsljv0hjjf5ioukshupb.apps.googleusercontent.com",
          "client_type": 3
        }
      ],
      "api_key": [
        {
          "current_key": "AIzaSyDmwchi6FsLqmbZOwk_GtDOFfAqFuJIamA"
        }
      ],
      "services": {
        "appinvite_service": {
          "other_platform_oauth_client": [
            {
              "client_id": "766736349135-i08p1gj8sj99vsljv0hjjf5ioukshupb.apps.googleusercontent.com",
              "client_type": 3
            }
          ]
        }
      }
    }
  ],
  "configuration_version": "1"
}